eia/__init__.py
eia/api_models.py
eia/client.py
eia-0.3.0.dist-info/LICENSE
eia-0.3.0.dist-info/METADATA
eia-0.3.0.dist-info/WHEEL
eia-0.3.0.dist-info/top_level.txt
eia-0.3.0.dist-info/RECORD
