Metadata-Version: 2.1
Name: eia
Version: 0.3.0
Summary: Client for interacting with the EIA API
Author: James Campbell
License: MIT License
Project-URL: Homepage, https://github.com/jcampbell/eia
Project-URL: Bug Tracker, https://github.com/jcampbell/eia/issues
Classifier: Programming Language :: Python :: 3
Classifier: License :: OSI Approved :: MIT License
Classifier: Operating System :: OS Independent
Requires-Python: >=3.9
License-File: LICENSE
Requires-Dist: requests (>=2.26.0)
Requires-Dist: pandas (>=1.0)
Requires-Dist: pydantic (>=1.7)
Requires-Dist: ratelimit (>=2.2.1)
